{
  "kind": "singleType",
  "collectionName": "contact_form_titles",
  "info": {
    "singularName": "contact-form-title",
    "pluralName": "contact-form-titles",
    "displayName": "ContactFormTitle",
    "description": ""
  },
  "options": {
    "draftAndPublish": true
  },
  "pluginOptions": {
    "i18n": {
      "localized": true
    }
  },
  "attributes": {
    "title": {
      "type": "string",
      "pluginOptions": {
        "i18n": {
          "localized": true
        }
      }
    }
  }
}
